[{"kind": "Listing", "data": {"after": null, "dist": 1, "modhash": "", "geo_filter": "", "children": [{"kind": "t3", "data": {"approved_at_utc": null, "subreddit": "HFY", "selftext": "**Author note: The Cryopod to Hell is a Reddit-exclusive story with over three years of editing and refining. As of this post, the total rewrite is _1,055,000+ words_ long, and we are all caught up to the main sub on HFY! For more information, check out the link below:**\n\n**[What is the Cryopod to Hell?](https://reddit.com/r/TheCryopodToHell/comments/d4t4or/new_readers_click_me_v2/)**\n\n**[Join the Cryoverse Discord server](https://discord.gg/xqBmwqj)!**\n\n**[Please support me on Patreon! Every dollar helps, as I have no job outside of Patreon currently!](https://www.patreon.com/klokinator)**\n\n**[Here's a list of all Cryopod's chapters, along with an ePub/Mobi/PDF version!](https://www.reddit.com/r/TheCryopodToHell/comments/8lu5j9/cryopod_refresh_index_list/)**\n\n...................................\n\n**([Previous Part](https://reddit.com/r/HFY/comments/iki80y/the_cryopod_to_hell_250_the_battle_brothers/))** \n\n**([Part 001](https://reddit.com/r/HFY/comments/d61d6t/the_cryopod_to_hell_001_entering_the_labyrinth/))**\n\n...\n\nMind, body, and soul. These are the three components that make up a living body; a being with intelligence, self-awareness, and the ability to contemplate their existence.\n\nAnd as of now, I am only two of those things: A soul with the will of a mind guiding it.\n\nThe universe flashes past me as I rush toward my destination, guided by my overriding command to 'Locate Phoebe Hiro.' Light-speed, warp-speed, and other such technical measures of velocity don't even begin to comprehend the blinding pace of a Wordsmithed flight. The power of magic surpasses reality, allowing me to race across the galaxy within seconds, traveling a ludicrous distance faster than any other non-magical method could ever allow.\n\nAll of a sudden, the stars whizzing past me at blistering speeds disappear. My soul-form lurches to an abrupt stop before a ball of blue and green hovering amidst the blackness of the void.\n\nTarus II.\n\nI stare at the planet for a moment, deliberately halting my advance to gaze at its splendor. Oceans cover some 80% of the planet's surface, with wild badlands far beyond the reach of Hero City, and another continent to the west, just at the edge of my vision. Humanity has yet to explore 5% of the world we reside upon, and someday, we will cover it with our population and turn it into a second Earth.\n\nThat notion assumes we will first survive whatever attack the demons have foisted upon us.\n\nI resume my course and rush at the planet's surface, heading toward the blinking pulse of mana indicating my wife's position.\n\nThe moment I break through the cloud cover, I slow my descent. The darkened night-time surface of Tarus's surface might normally be impossible for a pair of physical eyes to envision, but when I sweep my soul-vision around, I easily make out tens of thousands of pinpricks of light.\n\nTo the west, an undead army floods out of two colossal teleportation gates, while not far from them, countless demons surge from the Tarus II Warpgate as well. These enemies spread to the north, west, south, and east in droves, forcing the resistance fighters to envelop them to prevent leakage.\n\nHowever, what truly catches my attention are the 'soul glimmers' under the soil, deep beneath Tarus II's surface. Thousands of demons and undead swarm under the feet of the humans and monsters, my friends, all headed behind the back lines of the battlefield. Based on their positioning, it won't take the demons long before they can catch my friends in a pincer attack and prevent their escape!\n\nMy gaze hardens as I comprehend the devious plot of the bastards attacking my world.\n\nI gave Ose a choice. I extended a welcoming hand and offered her a chance to coexist with humanity. She replied with a backstab when I wasn't here to fight back.\n\nAnd why would she do such a thing?\n\nBecause she's a coward. She doesn't dare fight me head-on. Only by resorting to tricks and deceptions can she hope to brutalize humanity.\n\nI tried to play nice, but she repaid me with a slap to my face. \n\n_Unforgivable._\n\nWith rage clouding my vision, I zip over to Phoebe's position, only to come to a halt some distance away. To my shock, I find my wife battling alone against two insanely powerful magic users! Their mana burns a thousand times hotter than any other source nearby, making them appear to my soul-vision as twin suns irradiating the battlefield.\n\nAfter more than ten seconds of squinting, I finally recognize them.\n\nThe Battle Brothers! Kar's worst enemies, the bastards who murdered all of the crocodiles!\n\nYet what shocks me the most isn't that they've shown up, but that Kar isn't anywhere in the vicinity! Could it be? When Phoebe left a message, didn't she imply that the Battle Brothers somehow defeated Kar?!\n\nImpossible. Kar is extremely powerful, while the Battle Brothers are only Barons! Something else must have happened.\n\nAs I examine the battlefield, it occurs to me that, even without a real frame of reference, the Battle Brothers seem far stronger than any Barons I've seen before. Phoebe's armor, a heavily augmented exosuit Solomon helped her design several months ago, shreds the ground around both of the Battle Brothers with a triple-barreled minigun. The weapon fires countless bullets without cessation, its power stemming from the fact that its energy source is magical, not electrical. The bullets, comprised almost entirely from densely packed mana, get generated on the fly by a powerpack attached to the exosuit's back. This allows Phoebe to fire tens of thousands of bullets without so much as warming up the gun's barrel!\n\nI stay in the air and observe for a minute as the Battle Brothers dodge Phoebe's hailstorm of death and fury. They leap from left to right, backflip, and jump into the air, all while summoning ethereal weapons from an unknown dimension. Swords, axes, hammers, and maces smash and crash against Phoebe's armor, but not even so much as a scratch appears on the demonstone-infused nanites.\n\n\"You'll have to do better than that,\" Phoebe yells, taunting the Barons. \"Don't think you can leave here alive, you filthy mutts! All of you who attacked my world will die!\"\n\n\"Stop running your yap!\" Zamiel, the older Battle Brother, yells. He grabs a one-ton warhammer from his back and rushes at Phoebe, intending to bash her armor with all his strength.\n\nSuddenly, right before Zamiel can land his attack...\n\n_Foop!_\n\nThe Baron disappears and reappears half a foot backward, throwing off his aim. The Battle Brother misses and stumbles awkwardly, the weight of his swing sending him stumbling forward.\n\n\"Gahk! Shit! Fucking fairy! She's still here!\"\n\nI blink in surprise. \n\nDoes he mean... Blinker? Did she teleport him?\n\nThe moment the question pops into my head, I notice a flicker of mana not far behind Phoebe. A tiny but bright ball of mana hovers behind her back, the majority of its light concealed behind an illusory barrier.\n\nZamiel disappears. He teleports right into the path of Phoebe's minigun and gets blasted fifteen times in the blink of an eye, sending him screaming backwards, where he crashes into a massive puddle of drying blood. \"Aaargh!\"\n\n\"Bro? Bro!\" Duriel yells, shocked by this new development.\n\nI breathe a sigh of relief. With one Baron down, and beaten so easily, at that, it seems Phoebe won't have much issue dealing with the other one.\n\nMy wife seems to have the same idea. She turns to fight Duriel, only for Blinker's voice to speak from all around her. \"No! That Baron isn't dead, Phoebe! These Battle Brothers are weird! They can instantly heal any wound if they touch someone else's blood! I've never seen anything like it!\"\n\nToo late, by the time Blinker explains, Zamiel has already jumped back to his feet. The older Battle Brother breathes hard and glances at Duriel.\n\n\"We can't win, little bro! If it was just the human, this would be a piece of cake, but she has the Fairy Queen helping her! Let's get outta here!\"\n\n\"What? No! We can't run away, Zammy!\" Duriel guffaws. \"What'll the other demons say?!\"\n\n\"Screw the other demons!\" Zamiel howls. \"I don't give a shrakh what they say! Besides, we ain't running away! We're, uhh... we're executing a tactical retreat to return with reinforcements!\"\n\nPhoebe aims her minigun at Duriel and squeezes the trigger, but Duriel sees her attack coming and leaps straight into the air, narrowly avoiding death. With a quick flick of his fingers, he summons a gigantic flying greatsword beneath his feet and rides it like a surfboard.\n\n\"Shit! You almost got me! Alright bro, I'm gonna, uh, attack in the other direction! Yeah! You coming?\"\n\nZamiel replies by leaping onto the head of a massive flying hammer. He soars up to his brother and nods. \"Let's go!\"\n\nBefore the two of them can bail, a formless pressure suddenly grabs hold of Duriel.\n\n_Foop!_\n\nThe giant younger brother once again teleports into Phoebe's range, with his back directly in front of her minigun.\n\n\"Shrakh!\"\n\nBefore Duriel can react, Phoebe squeezes the trigger. A hail of bullets rips through his body, sending him staggering forward to collapse into the dirt.\n\nZamiel, still flying above, screams in rage. \"You bitch, that's cheating!\"\n\nI can almost hear Phoebe's smile through her voice. \"Haha. I told you... I won't let either of you leave alive. I always keep my promises!\"\n\nShe aims the barrel of the gun at the back of Duriel's head and squeezes the trigger.\n\n_BRRRRRT!_\n\nRight before the bullets burst his brain like a water balloon, Duriel's body turns into a shadow, as does Zamiel's.\n\nBoth Battle Brothers disappear, making Phoebe's bullets rip up the ground where Duriel laid only a moment before.\n\n\"What?! He vanished? How?!\"\n\n\"Stinky demon magic!\" Blinker chirps. She flies in front of Phoebe and sweeps her gaze around the area, but doesn't see anything.\n\n\"Who did that?\" Blinker mutters. \"Was it the Battle Brothers? A different demon? I don't know! Come on, Phoebe, we can't let them get away!\"\n\nBlinker, ready and rarring to go, starts to fly toward the horde of undead being kept at bay by the human commandos a few hundred feet to the west. However, Phoebe holds up her palm.\n\n\"No. Let them go for now, Blinker. I'm still injured and in a lot of pain.\"\n\nBlinker turns to look at Phoebe's giant, menacing exosuit. \"You are?\"\n\nPhoebe nods. \"After the Battle Brothers shot down my plane, I injured my leg pretty badly. I've temporarily patched it up with a nanite injection, but it still hurts like hell.\"\n\nWhile Phoebe and Blinker chat, I float a little lower to hear their conversation better. At that moment, Blinker suddenly flinches in fright and jerks her head upwards. She looks directly at me.\n\n\"Aaahh! A ghost! What the heck is that thing?!\"\n\nMy heart skips a beat. \"You can see me?! Blinker! It's me, Jason!\"\n\nBlinker starts to conjure magic, but she pauses mid-movement. \"Huh? Jason? What the heck! How can that be you? You're just a blob of light!\"\n\nI nod my head, only to feel strange about the motion, given I apparently don't have one. \n\n\"It's complicated. More importantly, I'm surprised you can see me in the first place. That's great, though, it helps me a lot. Can you tell Phoebe that I'm here? I want to get an update on what happened while I was... away.\"\n\nBlinker nods slowly, as a sparkle of light appears in her eyes. She turns to Phoebe and quickly relays everything I've said, making Phoebe raise her head to look in my general direction. \n\n\"What? Jason's here? Did you hit your head, Blinker? I don't see anything.\"\n\n\"He's in a soul-form for some reason,\" Blinker says, shrugging. \"I didn't even know I could see something like that!\"\n\n\"I, err, cast some extra magic on my soul before I left my body behind,\" I explain. \"It's complicated.\"\n\nI spend a few minutes catching up with Blinker while Phoebe stands guard, swiveling her minigun around to look for enemies. She continues guiding the allied army while I get the lowdown on the current situation, just so she isn't wasting any time or effort.\n\nEventually, Blinker nods.\n\n\"Wow, that's incredible. An artifact from the Primordial Era, and you even fought the Volgrim! What the heck, Jason? We thought you might have died, but instead, you were off having fun adventures! Meanie! You should have taken me along!\"\n\nI sigh. \"Sorry, uh, maybe next time. Look, I'm going to teleport back here in an hour or two. My body is currently constructing a device that will allow me to control Camael's Cube. Once it finishes, I can send it on its way and teleport back here to help. Until then, I'm just going to perform a little reconnaissance.\"\n\nBlinker nods, but her gaze darkens. \"You have to be careful, Jason. If I can see you, then it's possible someone among our enemies could, too. You can't Wordsmith in your soul-form, right? Don't risk your life all willy-nilly!\"\n\nI nod. \"Don't worry, I won't. Tell Phoebe everything I've told you. If Belial can't heal her, I will. I have more than enough mana to completely overwhelm the demons, now.\"\n\nI gnash my teeth together. \"I'll make those bastards _pay_ for coming here. They've killed too many of my friends! Once I show up, they'll rue the day they crossed me.\"\n\n\"Yeah!\" Blinker yells, while pumping her fist. \"That's the spirit! Alright, I have to help Phoebe manage the situation. Kar's still being healed by Sammy, so if you could check on him for me, I'd appreciate it.\"\n\n\"Sure,\" I say. \"Oh, and one more thing...\"\n\nBlinker listens intently as I tell her about the demons burrowing beneath our feet.\n\n\"Thanks for the heads-up, but we know! Phoebe has a bunch of mines buried around the battlefield. Whenever one goes off, it usually kills a Burrower, but more importantly, it tells us where those poopy-doops are digging! We've been able to follow their movements pretty well up to now.\"\n\n\"Great, glad to hear it,\" I say. I start to float upward, only to pause. \"Uh, can you, erm, tell Phoebe I love her and I'm sorry I didn't call for... however long it's been?\"\n\n\"Haha! You're so awkward!\" Blinker teases. \"Little lovebird wants me to tell his wifey that he loves her! Hahaha!\"\n\n\"Oh, shut up,\" I reply, blushing hard enough for my whole soul to turn red. \"Just tell her! Geez.\"\n\nI levitate skyward, leaving Blinker behind, all while her cackling laughter embarrasses me to no end.\n\n_When I get back, I'm gonna give that bratty little fairy a 'noogie.'_\n\n.......................................\n\nMinutes later, I begin darting around the battlefield at high speeds. With my Wordsmithed goal of 'locating Phoebe Hiro' complete, I regain full control of my soul's movements. To my astonishment, the speed of my soul is unbelievably fast. Unlike a physical body, with its biological limitations, my soul can travel across the galaxy in an instant, let alone any distance involving a mere planetary scale.\n\nI jump to the southern battlefield, where the undead flood against Lieutenant Samuel's force of 30,000 soldiers. The first thing I discover is that, unlike living demons, Mephisto's undead don't show up in my soul vision at all. A very small number do; the elites among elites, but the vast majority of them appear to be soulless, puppeteered bodies running on pure instinct. It makes me realize that Mephisto's forces are probably only a tenth as strong as when they were alive. Without a mind and soul to guide them, the river of undead are little more than drooling, angry bodies hellbent on killing and eating.\n\nAfter examining the stability of the southern situation, I jump to the west, where Mephisto's undead-summoning warpgates stand. Countless creatures swarm out, their type and strength a mixture from weak to strong. The western wall, now collapsed from god-only-knows what attacks, is little more than a pile of pulverized stone and steel. Demons and undead swarm over it to attack 20,000 exosuit-wearing soldiers, all of them firing ceaselessly with rapid-fire weapons into the fray.\n\nFinally, I flit over to the northern front. Here, a surprisingly firm defense of more than 50,000 soldiers, featuring a huge mixture of monsters as well as humans, hold firm against the demonic onslaught. Remembering the King Cannons atop the northern mountain range, it doesn't surprise me that Phoebe would put so much effort into defending the north compared to the south and west. Among the troopers, what catches my eye is Brunhilda's contingent of Felorians, all of them practitioners of a secret magical power known as _Chi_.\n\nBrunhilda's warriors rip through the demons and undead as if they were lava golems rampaging in the arctic. Her spear stabs, smashes, and pulverizes the heads of any undead that dare wander into her range.\n\nAs I fly overhead, for a brief moment, Brunhilda flicks her vision upward to look directly at me, making my heart jump. She lowers her gaze a moment later, making me wonder if it was simply a coincidence.\n\nAfterward, I disappear from the battlefield, my thoughts churning like crazy.\n\nNot only a high-ranking Volgrim, but a fairy and possibly a human can see my soul-form. That realization makes the hair stand up on the back of my neck. I'm not a purely ethereal being, but instead, something with tangibility that certain other beings can perceive. That means I have to be extra cautious in the future.\n\nWith merely a thought, I zip to the east, toward Hero City. Luckily, I don't spot any Burrowers underneath the city's limits.\n\nIn less than a second, I arrive at Hero City's western side, where the hospital stands, built at the edge of a two-hundred-foot cliff. When I fly inside, I spot hundreds of injured humans and monsters, some of them badly wounded and in critical condition. Almost mechanically, I try to Wordsmith and heal them, only to realize my efforts are futile.\n\nWhile flitting about, I spot one particular hospital room where the most critically wounded appear to be lined up outside. I slip inside to find Samantha pouring healing energy into a female soldier's body. The woman chokes out blood and coughs weakly, then offers Samantha a faint smile.\n\n\"Don't... don't blame yourself... you did the best... you...\"\n\nHer words cease, and her head lolls to the side. The woman passes away, and Samantha stops her healing magic.\n\nThe succubus stares silently at the dead soldier, a look of emptiness in her eyes. \"Rest in peace.\"\n\nExhaling deeply, Samantha nods at a morbidly obese demoness next to her. \"Rosalia. Bring in the next one.\"\n\n\"Yes, Emperor.\"\n\nI hover in the air and slowly wave my hand to try and get Samantha's attention, but she gazes stonily at the far wall and doesn't see me.\n\nSuddenly, a voice speaks up from the corner of the room behind me.\n\n\"Huh? Daddy?\"\n\nMy heart nearly jumps in fright! I turn to the side and spot Daisy sitting on a chair, looking directly at me with stars in her eyes.\n\n\"Daddy! It's daddy! He's here!\"\n\nDaisy jumps out of the chair and points at me excitedly. Her words shake Samantha out of her stupor. She looks at Daisy, then follows her finger to my general position. \"Huh? Daddy? Do you mean... Jason?\"\n\n\"Uh-huh!\" Daisy says, excitedly hopping up and down. \"He's right there, aunt S'matha! Can't you see him?!\"\n\nSamantha looks in my general direction, but her eyes pass through me. \"No, sweetheart. Maybe you need to get some sleep. You've been awake for almost two days.\"\n\nI'm not entirely sure why the heck my daughter can see me, but I'm still glad. I float down to her level and try to touch her face, only for my hand to pass through her cheek. \"Hey, sweetie. How are you holding up? Are you doing okay?\"\n\nDaisy nods excitedly. \"Yeah! Yeah! Me and aunt S'matha are healing all the hurt people! We just wave our hands and _WHOOSH_ all the boo-boos go away!\"\n\nSuddenly, Daisy hesitates. A look of horror appears in her eyes. \"W-why are you a ghost, daddy? Did... did you die?!\"\n\n\"No, no,\" I say quickly waving my hands. \"Daddy has magic, remember? I used my magic to make a ghost-body, just so I could say hi to my little girl. Right now I'm really far away, but I'll come back very soon, okay?\"\n\nSamantha watches with a puzzled expression while Daisy babbles at the air, but her only response is to slowly shake her head. It's clear from just one look that she thinks Daisy must be hallucinating my existence.\n\nAfter I finish reassuring Daisy that her daddy _definitely_ isn't dead, I say, \"Oh, and tell aunt Samantha that daddy says hi, okay? Uh, tell her that mommy is fine, too. She got hurt a little bit, but daddy will definitely take care of her.\"\n\nDaisy nods furiously. \"Okay! I love you, daddy! Come back soon!\"\n\n\"I love you too, sweetheart.\"\n\nI try to kiss Daisy's head, but my face awkwardly melts through her skull, allowing me to see her brains. _Ew!_\n\nWith a shudder, I fly into the sky and disappear through the roof, leaving Daisy and Samantha behind.\n\n...\n\nAnother few minutes later, I zip around the eastern side of Hero City. After scouting the area, I ready myself to return to Blinker to let her know about the situation outside the battlefield, only for my stomach to flip-flop in alarm!\n\nOnly a mile away from Hero City, several 'blips' of soul energy show up within my vision range. I fly closer and gasp as I spot three glowing beacons of demonic mana standing around, talking to one another. The moment I get close enough, I listen intently to make out their conversation.\n\nA demoness clothed in long, gray robes, growls at a male nearby. \"-the signal. I think we should summon the gates now. We've already got the city surrounded. Once we build up our forces, we can rush the barrier all at once.\"\n\n\"Ose's orders are absolute,\" The male says, his garb a green-colored bunch of robes. \"We're only Warpers. We don't have the authority to override Emperor Ose. Do you think you're smarter than her?\"\n\nThe female's expression crumples. \"...No.\"\n\n\"Then shut your trap and wait for the signal.\"\n\nMy heart skips several beats as I gather that these three demons must have somehow skirted around the battlefield and slipped into our backlines! They're waiting to open portals so they can attack us!\n\nWhile I listen, my gaze falls on the third mana signature belonging to the demon who hasn't spoken yet. To my surprise, not only is their mana signal far brighter than the other two, but the Warpers don't look at the other demon for even a moment, as if that demon's presence were invisible.\n\nI draw a little closer and blink in surprise.\n\nThe third demon stands with their back to me. However, what surprises me the most is that my gaze pierces through part of their body!\n\nWith a start, I suddenly realize the other demon isn't really there! Whoever they are, their presence is almost holographic and immaterial in nature, like me! They might be a fellow errant soul!\n\nThe moment I have this epiphany, the third demon suddenly stiffens. They turn around to look at me, revealing the face of a very familiar woman.\n\n_Ose!_\n\nThe Emperor of Infiltration stares at me for a moment and blanks out. \"Hm? Another Astral Body? Who the Devil are you?\"\n\nIn the blink of an eye, she rushes toward me, a look of venomous murder on her face. She soars into the sky and balls her hands into fists, aiming to pummel me into a bloody pulp. The instant before Ose arrives, she suddenly stops and reverses direction, her angry expression turning to shock and horror.\n\n\"What?! The Wordsmith?!\"\n\nMy heart explodes with hatred and rage. I've suddenly stumbled upon a prime opportunity I never expected! Ose, now in a soul-body like mine, hovers mere feet away, clearly alarmed by my presence.\n\n\"Hello, _Ose._ Seems you've been up to no good.\"\n\nOse gnashes her teeth. \"Tch! How dare you step within my domain, the Astral Realm! Now that you've seen my Astral Body, you've sealed your fate, Wordsmith!\"\n\nI shake my head.\n\n\"Oh, I don't think so.\"\n\n**[Next Part](https://reddit.com/r/HFY/comments/iorzqa/the_cryopod_to_hell_252_astral_souleater/?)**", "user_reports": [], "saved": false, "mod_reason_title": null, "gilded": 0, "clicked": false, "title": "The Cryopod to Hell 251: Swift Soul Searching", "link_flair_richtext": [], "subreddit_name_prefixed": "r/HFY", "hidden": false, "pwls": 7, "link_flair_css_class": "OC", "downs": 0, "top_awarded_type": null, "hide_score": false, "name": "t3_imz7sa", "quarantine": false, "link_flair_text_color": "dark", "upvote_ratio": 0.96, "author_flair_background_color": null, "subreddit_type": "public", "ups": 78, "total_awards_received": 0, "media_embed": {}, "author_flair_template_id": "f2ef2e52-57dc-11e4-908c-12313b0e5086", "is_original_content": true, "author_fullname": "t2_fbfvm", "secure_media": null, "is_reddit_media_domain": false, "is_meta": false, "category": null, "secure_media_embed": {}, "link_flair_text": "OC", "can_mod_post": false, "score": 78, "approved_by": null, "is_created_from_ads_ui": false, "author_premium": false, "thumbnail": "", "edited": 1633406044.0, "author_flair_css_class": null, "author_flair_richtext": [], "gildings": {}, "content_categories": ["writing"], "is_self": true, "mod_note": null, "created": 1599303393.0, "link_flair_type": "text", "wls": 7, "removed_by_category": null, "banned_by": null, "author_flair_type": "text", "domain": "self.HFY", "allow_live_comments": false, "selftext_html": "&lt;!-- SC_OFF --&gt;&lt;div class=\"md\"&gt;&lt;p&gt;&lt;strong&gt;Author note: The Cryopod to Hell is a Reddit-exclusive story with over three years of editing and refining. As of this post, the total rewrite is &lt;em&gt;1,055,000+ words&lt;/em&gt; long, and we are all caught up to the main sub on HFY! For more information, check out the link below:&lt;/strong&gt;&lt;/p&gt;\n\n&lt;p&gt;&lt;strong&gt;&lt;a href=\"https://reddit.com/r/TheCryopodToHell/comments/d4t4or/new_readers_click_me_v2/\"&gt;What is the Cryopod to Hell?&lt;/a&gt;&lt;/strong&gt;&lt;/p&gt;\n\n&lt;p&gt;&lt;strong&gt;&lt;a href=\"https://discord.gg/xqBmwqj\"&gt;Join the Cryoverse Discord server&lt;/a&gt;!&lt;/strong&gt;&lt;/p&gt;\n\n&lt;p&gt;&lt;strong&gt;&lt;a href=\"https://www.patreon.com/klokinator\"&gt;Please support me on Patreon! Every dollar helps, as I have no job outside of Patreon currently!&lt;/a&gt;&lt;/strong&gt;&lt;/p&gt;\n\n&lt;p&gt;&lt;strong&gt;&lt;a href=\"https://www.reddit.com/r/TheCryopodToHell/comments/8lu5j9/cryopod_refresh_index_list/\"&gt;Here&amp;#39;s a list of all Cryopod&amp;#39;s chapters, along with an ePub/Mobi/PDF version!&lt;/a&gt;&lt;/strong&gt;&lt;/p&gt;\n\n&lt;p&gt;...................................&lt;/p&gt;\n\n&lt;p&gt;&lt;strong&gt;(&lt;a href=\"https://reddit.com/r/HFY/comments/iki80y/the_cryopod_to_hell_250_the_battle_brothers/\"&gt;Previous Part&lt;/a&gt;)&lt;/strong&gt; &lt;/p&gt;\n\n&lt;p&gt;&lt;strong&gt;(&lt;a href=\"https://reddit.com/r/HFY/comments/d61d6t/the_cryopod_to_hell_001_entering_the_labyrinth/\"&gt;Part 001&lt;/a&gt;)&lt;/strong&gt;&lt;/p&gt;\n\n&lt;p&gt;...&lt;/p&gt;\n\n&lt;p&gt;Mind, body, and soul. These are the three components that make up a living body; a being with intelligence, self-awareness, and the ability to contemplate their existence.&lt;/p&gt;\n\n&lt;p&gt;And as of now, I am only two of those things: A soul with the will of a mind guiding it.&lt;/p&gt;\n\n&lt;p&gt;The universe flashes past me as I rush toward my destination, guided by my overriding command to &amp;#39;Locate Phoebe Hiro.&amp;#39; Light-speed, warp-speed, and other such technical measures of velocity don&amp;#39;t even begin to comprehend the blinding pace of a Wordsmithed flight. The power of magic surpasses reality, allowing me to race across the galaxy within seconds, traveling a ludicrous distance faster than any other non-magical method could ever allow.&lt;/p&gt;\n\n&lt;p&gt;All of a sudden, the stars whizzing past me at blistering speeds disappear. My soul-form lurches to an abrupt stop before a ball of blue and green hovering amidst the blackness of the void.&lt;/p&gt;\n\n&lt;p&gt;Tarus II.&lt;/p&gt;\n\n&lt;p&gt;I stare at the planet for a moment, deliberately halting my advance to gaze at its splendor. Oceans cover some 80% of the planet&amp;#39;s surface, with wild badlands far beyond the reach of Hero City, and another continent to the west, just at the edge of my vision. Humanity has yet to explore 5% of the world we reside upon, and someday, we will cover it with our population and turn it into a second Earth.&lt;/p&gt;\n\n&lt;p&gt;That notion assumes we will first survive whatever attack the demons have foisted upon us.&lt;/p&gt;\n\n&lt;p&gt;I resume my course and rush at the planet&amp;#39;s surface, heading toward the blinking pulse of mana indicating my wife&amp;#39;s position.&lt;/p&gt;\n\n&lt;p&gt;The moment I break through the cloud cover, I slow my descent. The darkened night-time surface of Tarus&amp;#39;s surface might normally be impossible for a pair of physical eyes to envision, but when I sweep my soul-vision around, I easily make out tens of thousands of pinpricks of light.&lt;/p&gt;\n\n&lt;p&gt;To the west, an undead army floods out of two colossal teleportation gates, while not far from them, countless demons surge from the Tarus II Warpgate as well. These enemies spread to the north, west, south, and east in droves, forcing the resistance fighters to envelop them to prevent leakage.&lt;/p&gt;\n\n&lt;p&gt;However, what truly catches my attention are the &amp;#39;soul glimmers&amp;#39; under the soil, deep beneath Tarus II&amp;#39;s surface. Thousands of demons and undead swarm under the feet of the humans and monsters, my friends, all headed behind the back lines of the battlefield. Based on their positioning, it won&amp;#39;t take the demons long before they can catch my friends in a pincer attack and prevent their escape!&lt;/p&gt;\n\n&lt;p&gt;My gaze hardens as I comprehend the devious plot of the bastards attacking my world.&lt;/p&gt;\n\n&lt;p&gt;I gave Ose a choice. I extended a welcoming hand and offered her a chance to coexist with humanity. She replied with a backstab when I wasn&amp;#39;t here to fight back.&lt;/p&gt;\n\n&lt;p&gt;And why would she do such a thing?&lt;/p&gt;\n\n&lt;p&gt;Because she&amp;#39;s a coward. She doesn&amp;#39;t dare fight me head-on. Only by resorting to tricks and deceptions can she hope to brutalize humanity.&lt;/p&gt;\n\n&lt;p&gt;I tried to play nice, but she repaid me with a slap to my face. &lt;/p&gt;\n\n&lt;p&gt;&lt;em&gt;Unforgivable.&lt;/em&gt;&lt;/p&gt;\n\n&lt;p&gt;With rage clouding my vision, I zip over to Phoebe&amp;#39;s position, only to come to a halt some distance away. To my shock, I find my wife battling alone against two insanely powerful magic users! Their mana burns a thousand times hotter than any other source nearby, making them appear to my soul-vision as twin suns irradiating the battlefield.&lt;/p&gt;\n\n&lt;p&gt;After more than ten seconds of squinting, I finally recognize them.&lt;/p&gt;\n\n&lt;p&gt;The Battle Brothers! Kar&amp;#39;s worst enemies, the bastards who murdered all of the crocodiles!&lt;/p&gt;\n\n&lt;p&gt;Yet what shocks me the most isn&amp;#39;t that they&amp;#39;ve shown up, but that Kar isn&amp;#39;t anywhere in the vicinity! Could it be? When Phoebe left a message, didn&amp;#39;t she imply that the Battle Brothers somehow defeated Kar?!&lt;/p&gt;\n\n&lt;p&gt;Impossible. Kar is extremely powerful, while the Battle Brothers are only Barons! Something else must have happened.&lt;/p&gt;\n\n&lt;p&gt;As I examine the battlefield, it occurs to me that, even without a real frame of reference, the Battle Brothers seem far stronger than any Barons I&amp;#39;ve seen before. Phoebe&amp;#39;s armor, a heavily augmented exosuit Solomon helped her design several months ago, shreds the ground around both of the Battle Brothers with a triple-barreled minigun. The weapon fires countless bullets without cessation, its power stemming from the fact that its energy source is magical, not electrical. The bullets, comprised almost entirely from densely packed mana, get generated on the fly by a powerpack attached to the exosuit&amp;#39;s back. This allows Phoebe to fire tens of thousands of bullets without so much as warming up the gun&amp;#39;s barrel!&lt;/p&gt;\n\n&lt;p&gt;I stay in the air and observe for a minute as the Battle Brothers dodge Phoebe&amp;#39;s hailstorm of death and fury. They leap from left to right, backflip, and jump into the air, all while summoning ethereal weapons from an unknown dimension. Swords, axes, hammers, and maces smash and crash against Phoebe&amp;#39;s armor, but not even so much as a scratch appears on the demonstone-infused nanites.&lt;/p&gt;\n\n&lt;p&gt;&amp;quot;You&amp;#39;ll have to do better than that,&amp;quot; Phoebe yells, taunting the Barons. &amp;quot;Don&amp;#39;t think you can leave here alive, you filthy mutts! All of you who attacked my world will die!&amp;quot;&lt;/p&gt;\n\n&lt;p&gt;&amp;quot;Stop running your yap!&amp;quot; Zamiel, the older Battle Brother, yells. He grabs a one-ton warhammer from his back and rushes at Phoebe, intending to bash her armor with all his strength.&lt;/p&gt;\n\n&lt;p&gt;Suddenly, right before Zamiel can land his attack...&lt;/p&gt;\n\n&lt;p&gt;&lt;em&gt;Foop!&lt;/em&gt;&lt;/p&gt;\n\n&lt;p&gt;The Baron disappears and reappears half a foot backward, throwing off his aim. The Battle Brother misses and stumbles awkwardly, the weight of his swing sending him stumbling forward.&lt;/p&gt;\n\n&lt;p&gt;&amp;quot;Gahk! Shit! Fucking fairy! She&amp;#39;s still here!&amp;quot;&lt;/p&gt;\n\n&lt;p&gt;I blink in surprise. &lt;/p&gt;\n\n&lt;p&gt;Does he mean... Blinker? Did she teleport him?&lt;/p&gt;\n\n&lt;p&gt;The moment the question pops into my head, I notice a flicker of mana not far behind Phoebe. A tiny but bright ball of mana hovers behind her back, the majority of its light concealed behind an illusory barrier.&lt;/p&gt;\n\n&lt;p&gt;Zamiel disappears. He teleports right into the path of Phoebe&amp;#39;s minigun and gets blasted fifteen times in the blink of an eye, sending him screaming backwards, where he crashes into a massive puddle of drying blood. &amp;quot;Aaargh!&amp;quot;&lt;/p&gt;\n\n&lt;p&gt;&amp;quot;Bro? Bro!&amp;quot; Duriel yells, shocked by this new development.&lt;/p&gt;\n\n&lt;p&gt;I breathe a sigh of relief. With one Baron down, and beaten so easily, at that, it seems Phoebe won&amp;#39;t have much issue dealing with the other one.&lt;/p&gt;\n\n&lt;p&gt;My wife seems to have the same idea. She turns to fight Duriel, only for Blinker&amp;#39;s voice to speak from all around her. &amp;quot;No! That Baron isn&amp;#39;t dead, Phoebe! These Battle Brothers are weird! They can instantly heal any wound if they touch someone else&amp;#39;s blood! I&amp;#39;ve never seen anything like it!&amp;quot;&lt;/p&gt;\n\n&lt;p&gt;Too late, by the time Blinker explains, Zamiel has already jumped back to his feet. The older Battle Brother breathes hard and glances at Duriel.&lt;/p&gt;\n\n&lt;p&gt;&amp;quot;We can&amp;#39;t win, little bro! If it was just the human, this would be a piece of cake, but she has the Fairy Queen helping her! Let&amp;#39;s get outta here!&amp;quot;&lt;/p&gt;\n\n&lt;p&gt;&amp;quot;What? No! We can&amp;#39;t run away, Zammy!&amp;quot; Duriel guffaws. &amp;quot;What&amp;#39;ll the other demons say?!&amp;quot;&lt;/p&gt;\n\n&lt;p&gt;&amp;quot;Screw the other demons!&amp;quot; Zamiel howls. &amp;quot;I don&amp;#39;t give a shrakh what they say! Besides, we ain&amp;#39;t running away! We&amp;#39;re, uhh... we&amp;#39;re executing a tactical retreat to return with reinforcements!&amp;quot;&lt;/p&gt;\n\n&lt;p&gt;Phoebe aims her minigun at Duriel and squeezes the trigger, but Duriel sees her attack coming and leaps straight into the air, narrowly avoiding death. With a quick flick of his fingers, he summons a gigantic flying greatsword beneath his feet and rides it like a surfboard.&lt;/p&gt;\n\n&lt;p&gt;&amp;quot;Shit! You almost got me! Alright bro, I&amp;#39;m gonna, uh, attack in the other direction! Yeah! You coming?&amp;quot;&lt;/p&gt;\n\n&lt;p&gt;Zamiel replies by leaping onto the head of a massive flying hammer. He soars up to his brother and nods. &amp;quot;Let&amp;#39;s go!&amp;quot;&lt;/p&gt;\n\n&lt;p&gt;Before the two of them can bail, a formless pressure suddenly grabs hold of Duriel.&lt;/p&gt;\n\n&lt;p&gt;&lt;em&gt;Foop!&lt;/em&gt;&lt;/p&gt;\n\n&lt;p&gt;The giant younger brother once again teleports into Phoebe&amp;#39;s range, with his back directly in front of her minigun.&lt;/p&gt;\n\n&lt;p&gt;&amp;quot;Shrakh!&amp;quot;&lt;/p&gt;\n\n&lt;p&gt;Before Duriel can react, Phoebe squeezes the trigger. A hail of bullets rips through his body, sending him staggering forward to collapse into the dirt.&lt;/p&gt;\n\n&lt;p&gt;Zamiel, still flying above, screams in rage. &amp;quot;You bitch, that&amp;#39;s cheating!&amp;quot;&lt;/p&gt;\n\n&lt;p&gt;I can almost hear Phoebe&amp;#39;s smile through her voice. &amp;quot;Haha. I told you... I won&amp;#39;t let either of you leave alive. I always keep my promises!&amp;quot;&lt;/p&gt;\n\n&lt;p&gt;She aims the barrel of the gun at the back of Duriel&amp;#39;s head and squeezes the trigger.&lt;/p&gt;\n\n&lt;p&gt;&lt;em&gt;BRRRRRT!&lt;/em&gt;&lt;/p&gt;\n\n&lt;p&gt;Right before the bullets burst his brain like a water balloon, Duriel&amp;#39;s body turns into a shadow, as does Zamiel&amp;#39;s.&lt;/p&gt;\n\n&lt;p&gt;Both Battle Brothers disappear, making Phoebe&amp;#39;s bullets rip up the ground where Duriel laid only a moment before.&lt;/p&gt;\n\n&lt;p&gt;&amp;quot;What?! He vanished? How?!&amp;quot;&lt;/p&gt;\n\n&lt;p&gt;&amp;quot;Stinky demon magic!&amp;quot; Blinker chirps. She flies in front of Phoebe and sweeps her gaze around the area, but doesn&amp;#39;t see anything.&lt;/p&gt;\n\n&lt;p&gt;&amp;quot;Who did that?&amp;quot; Blinker mutters. &amp;quot;Was it the Battle Brothers? A different demon? I don&amp;#39;t know! Come on, Phoebe, we can&amp;#39;t let them get away!&amp;quot;&lt;/p&gt;\n\n&lt;p&gt;Blinker, ready and rarring to go, starts to fly toward the horde of undead being kept at bay by the human commandos a few hundred feet to the west. However, Phoebe holds up her palm.&lt;/p&gt;\n\n&lt;p&gt;&amp;quot;No. Let them go for now, Blinker. I&amp;#39;m still injured and in a lot of pain.&amp;quot;&lt;/p&gt;\n\n&lt;p&gt;Blinker turns to look at Phoebe&amp;#39;s giant, menacing exosuit. &amp;quot;You are?&amp;quot;&lt;/p&gt;\n\n&lt;p&gt;Phoebe nods. &amp;quot;After the Battle Brothers shot down my plane, I injured my leg pretty badly. I&amp;#39;ve temporarily patched it up with a nanite injection, but it still hurts like hell.&amp;quot;&lt;/p&gt;\n\n&lt;p&gt;While Phoebe and Blinker chat, I float a little lower to hear their conversation better. At that moment, Blinker suddenly flinches in fright and jerks her head upwards. She looks directly at me.&lt;/p&gt;\n\n&lt;p&gt;&amp;quot;Aaahh! A ghost! What the heck is that thing?!&amp;quot;&lt;/p&gt;\n\n&lt;p&gt;My heart skips a beat. &amp;quot;You can see me?! Blinker! It&amp;#39;s me, Jason!&amp;quot;&lt;/p&gt;\n\n&lt;p&gt;Blinker starts to conjure magic, but she pauses mid-movement. &amp;quot;Huh? Jason? What the heck! How can that be you? You&amp;#39;re just a blob of light!&amp;quot;&lt;/p&gt;\n\n&lt;p&gt;I nod my head, only to feel strange about the motion, given I apparently don&amp;#39;t have one. &lt;/p&gt;\n\n&lt;p&gt;&amp;quot;It&amp;#39;s complicated. More importantly, I&amp;#39;m surprised you can see me in the first place. That&amp;#39;s great, though, it helps me a lot. Can you tell Phoebe that I&amp;#39;m here? I want to get an update on what happened while I was... away.&amp;quot;&lt;/p&gt;\n\n&lt;p&gt;Blinker nods slowly, as a sparkle of light appears in her eyes. She turns to Phoebe and quickly relays everything I&amp;#39;ve said, making Phoebe raise her head to look in my general direction. &lt;/p&gt;\n\n&lt;p&gt;&amp;quot;What? Jason&amp;#39;s here? Did you hit your head, Blinker? I don&amp;#39;t see anything.&amp;quot;&lt;/p&gt;\n\n&lt;p&gt;&amp;quot;He&amp;#39;s in a soul-form for some reason,&amp;quot; Blinker says, shrugging. &amp;quot;I didn&amp;#39;t even know I could see something like that!&amp;quot;&lt;/p&gt;\n\n&lt;p&gt;&amp;quot;I, err, cast some extra magic on my soul before I left my body behind,&amp;quot; I explain. &amp;quot;It&amp;#39;s complicated.&amp;quot;&lt;/p&gt;\n\n&lt;p&gt;I spend a few minutes catching up with Blinker while Phoebe stands guard, swiveling her minigun around to look for enemies. She continues guiding the allied army while I get the lowdown on the current situation, just so she isn&amp;#39;t wasting any time or effort.&lt;/p&gt;\n\n&lt;p&gt;Eventually, Blinker nods.&lt;/p&gt;\n\n&lt;p&gt;&amp;quot;Wow, that&amp;#39;s incredible. An artifact from the Primordial Era, and you even fought the Volgrim! What the heck, Jason? We thought you might have died, but instead, you were off having fun adventures! Meanie! You should have taken me along!&amp;quot;&lt;/p&gt;\n\n&lt;p&gt;I sigh. &amp;quot;Sorry, uh, maybe next time. Look, I&amp;#39;m going to teleport back here in an hour or two. My body is currently constructing a device that will allow me to control Camael&amp;#39;s Cube. Once it finishes, I can send it on its way and teleport back here to help. Until then, I&amp;#39;m just going to perform a little reconnaissance.&amp;quot;&lt;/p&gt;\n\n&lt;p&gt;Blinker nods, but her gaze darkens. &amp;quot;You have to be careful, Jason. If I can see you, then it&amp;#39;s possible someone among our enemies could, too. You can&amp;#39;t Wordsmith in your soul-form, right? Don&amp;#39;t risk your life all willy-nilly!&amp;quot;&lt;/p&gt;\n\n&lt;p&gt;I nod. &amp;quot;Don&amp;#39;t worry, I won&amp;#39;t. Tell Phoebe everything I&amp;#39;ve told you. If Belial can&amp;#39;t heal her, I will. I have more than enough mana to completely overwhelm the demons, now.&amp;quot;&lt;/p&gt;\n\n&lt;p&gt;I gnash my teeth together. &amp;quot;I&amp;#39;ll make those bastards &lt;em&gt;pay&lt;/em&gt; for coming here. They&amp;#39;ve killed too many of my friends! Once I show up, they&amp;#39;ll rue the day they crossed me.&amp;quot;&lt;/p&gt;\n\n&lt;p&gt;&amp;quot;Yeah!&amp;quot; Blinker yells, while pumping her fist. &amp;quot;That&amp;#39;s the spirit! Alright, I have to help Phoebe manage the situation. Kar&amp;#39;s still being healed by Sammy, so if you could check on him for me, I&amp;#39;d appreciate it.&amp;quot;&lt;/p&gt;\n\n&lt;p&gt;&amp;quot;Sure,&amp;quot; I say. &amp;quot;Oh, and one more thing...&amp;quot;&lt;/p&gt;\n\n&lt;p&gt;Blinker listens intently as I tell her about the demons burrowing beneath our feet.&lt;/p&gt;\n\n&lt;p&gt;&amp;quot;Thanks for the heads-up, but we know! Phoebe has a bunch of mines buried around the battlefield. Whenever one goes off, it usually kills a Burrower, but more importantly, it tells us where those poopy-doops are digging! We&amp;#39;ve been able to follow their movements pretty well up to now.&amp;quot;&lt;/p&gt;\n\n&lt;p&gt;&amp;quot;Great, glad to hear it,&amp;quot; I say. I start to float upward, only to pause. &amp;quot;Uh, can you, erm, tell Phoebe I love her and I&amp;#39;m sorry I didn&amp;#39;t call for... however long it&amp;#39;s been?&amp;quot;&lt;/p&gt;\n\n&lt;p&gt;&amp;quot;Haha! You&amp;#39;re so awkward!&amp;quot; Blinker teases. &amp;quot;Little lovebird wants me to tell his wifey that he loves her! Hahaha!&amp;quot;&lt;/p&gt;\n\n&lt;p&gt;&amp;quot;Oh, shut up,&amp;quot; I reply, blushing hard enough for my whole soul to turn red. &amp;quot;Just tell her! Geez.&amp;quot;&lt;/p&gt;\n\n&lt;p&gt;I levitate skyward, leaving Blinker behind, all while her cackling laughter embarrasses me to no end.&lt;/p&gt;\n\n&lt;p&gt;&lt;em&gt;When I get back, I&amp;#39;m gonna give that bratty little fairy a &amp;#39;noogie.&amp;#39;&lt;/em&gt;&lt;/p&gt;\n\n&lt;p&gt;.......................................&lt;/p&gt;\n\n&lt;p&gt;Minutes later, I begin darting around the battlefield at high speeds. With my Wordsmithed goal of &amp;#39;locating Phoebe Hiro&amp;#39; complete, I regain full control of my soul&amp;#39;s movements. To my astonishment, the speed of my soul is unbelievably fast. Unlike a physical body, with its biological limitations, my soul can travel across the galaxy in an instant, let alone any distance involving a mere planetary scale.&lt;/p&gt;\n\n&lt;p&gt;I jump to the southern battlefield, where the undead flood against Lieutenant Samuel&amp;#39;s force of 30,000 soldiers. The first thing I discover is that, unlike living demons, Mephisto&amp;#39;s undead don&amp;#39;t show up in my soul vision at all. A very small number do; the elites among elites, but the vast majority of them appear to be soulless, puppeteered bodies running on pure instinct. It makes me realize that Mephisto&amp;#39;s forces are probably only a tenth as strong as when they were alive. Without a mind and soul to guide them, the river of undead are little more than drooling, angry bodies hellbent on killing and eating.&lt;/p&gt;\n\n&lt;p&gt;After examining the stability of the southern situation, I jump to the west, where Mephisto&amp;#39;s undead-summoning warpgates stand. Countless creatures swarm out, their type and strength a mixture from weak to strong. The western wall, now collapsed from god-only-knows what attacks, is little more than a pile of pulverized stone and steel. Demons and undead swarm over it to attack 20,000 exosuit-wearing soldiers, all of them firing ceaselessly with rapid-fire weapons into the fray.&lt;/p&gt;\n\n&lt;p&gt;Finally, I flit over to the northern front. Here, a surprisingly firm defense of more than 50,000 soldiers, featuring a huge mixture of monsters as well as humans, hold firm against the demonic onslaught. Remembering the King Cannons atop the northern mountain range, it doesn&amp;#39;t surprise me that Phoebe would put so much effort into defending the north compared to the south and west. Among the troopers, what catches my eye is Brunhilda&amp;#39;s contingent of Felorians, all of them practitioners of a secret magical power known as &lt;em&gt;Chi&lt;/em&gt;.&lt;/p&gt;\n\n&lt;p&gt;Brunhilda&amp;#39;s warriors rip through the demons and undead as if they were lava golems rampaging in the arctic. Her spear stabs, smashes, and pulverizes the heads of any undead that dare wander into her range.&lt;/p&gt;\n\n&lt;p&gt;As I fly overhead, for a brief moment, Brunhilda flicks her vision upward to look directly at me, making my heart jump. She lowers her gaze a moment later, making me wonder if it was simply a coincidence.&lt;/p&gt;\n\n&lt;p&gt;Afterward, I disappear from the battlefield, my thoughts churning like crazy.&lt;/p&gt;\n\n&lt;p&gt;Not only a high-ranking Volgrim, but a fairy and possibly a human can see my soul-form. That realization makes the hair stand up on the back of my neck. I&amp;#39;m not a purely ethereal being, but instead, something with tangibility that certain other beings can perceive. That means I have to be extra cautious in the future.&lt;/p&gt;\n\n&lt;p&gt;With merely a thought, I zip to the east, toward Hero City. Luckily, I don&amp;#39;t spot any Burrowers underneath the city&amp;#39;s limits.&lt;/p&gt;\n\n&lt;p&gt;In less than a second, I arrive at Hero City&amp;#39;s western side, where the hospital stands, built at the edge of a two-hundred-foot cliff. When I fly inside, I spot hundreds of injured humans and monsters, some of them badly wounded and in critical condition. Almost mechanically, I try to Wordsmith and heal them, only to realize my efforts are futile.&lt;/p&gt;\n\n&lt;p&gt;While flitting about, I spot one particular hospital room where the most critically wounded appear to be lined up outside. I slip inside to find Samantha pouring healing energy into a female soldier&amp;#39;s body. The woman chokes out blood and coughs weakly, then offers Samantha a faint smile.&lt;/p&gt;\n\n&lt;p&gt;&amp;quot;Don&amp;#39;t... don&amp;#39;t blame yourself... you did the best... you...&amp;quot;&lt;/p&gt;\n\n&lt;p&gt;Her words cease, and her head lolls to the side. The woman passes away, and Samantha stops her healing magic.&lt;/p&gt;\n\n&lt;p&gt;The succubus stares silently at the dead soldier, a look of emptiness in her eyes. &amp;quot;Rest in peace.&amp;quot;&lt;/p&gt;\n\n&lt;p&gt;Exhaling deeply, Samantha nods at a morbidly obese demoness next to her. &amp;quot;Rosalia. Bring in the next one.&amp;quot;&lt;/p&gt;\n\n&lt;p&gt;&amp;quot;Yes, Emperor.&amp;quot;&lt;/p&gt;\n\n&lt;p&gt;I hover in the air and slowly wave my hand to try and get Samantha&amp;#39;s attention, but she gazes stonily at the far wall and doesn&amp;#39;t see me.&lt;/p&gt;\n\n&lt;p&gt;Suddenly, a voice speaks up from the corner of the room behind me.&lt;/p&gt;\n\n&lt;p&gt;&amp;quot;Huh? Daddy?&amp;quot;&lt;/p&gt;\n\n&lt;p&gt;My heart nearly jumps in fright! I turn to the side and spot Daisy sitting on a chair, looking directly at me with stars in her eyes.&lt;/p&gt;\n\n&lt;p&gt;&amp;quot;Daddy! It&amp;#39;s daddy! He&amp;#39;s here!&amp;quot;&lt;/p&gt;\n\n&lt;p&gt;Daisy jumps out of the chair and points at me excitedly. Her words shake Samantha out of her stupor. She looks at Daisy, then follows her finger to my general position. &amp;quot;Huh? Daddy? Do you mean... Jason?&amp;quot;&lt;/p&gt;\n\n&lt;p&gt;&amp;quot;Uh-huh!&amp;quot; Daisy says, excitedly hopping up and down. &amp;quot;He&amp;#39;s right there, aunt S&amp;#39;matha! Can&amp;#39;t you see him?!&amp;quot;&lt;/p&gt;\n\n&lt;p&gt;Samantha looks in my general direction, but her eyes pass through me. &amp;quot;No, sweetheart. Maybe you need to get some sleep. You&amp;#39;ve been awake for almost two days.&amp;quot;&lt;/p&gt;\n\n&lt;p&gt;I&amp;#39;m not entirely sure why the heck my daughter can see me, but I&amp;#39;m still glad. I float down to her level and try to touch her face, only for my hand to pass through her cheek. &amp;quot;Hey, sweetie. How are you holding up? Are you doing okay?&amp;quot;&lt;/p&gt;\n\n&lt;p&gt;Daisy nods excitedly. &amp;quot;Yeah! Yeah! Me and aunt S&amp;#39;matha are healing all the hurt people! We just wave our hands and &lt;em&gt;WHOOSH&lt;/em&gt; all the boo-boos go away!&amp;quot;&lt;/p&gt;\n\n&lt;p&gt;Suddenly, Daisy hesitates. A look of horror appears in her eyes. &amp;quot;W-why are you a ghost, daddy? Did... did you die?!&amp;quot;&lt;/p&gt;\n\n&lt;p&gt;&amp;quot;No, no,&amp;quot; I say quickly waving my hands. &amp;quot;Daddy has magic, remember? I used my magic to make a ghost-body, just so I could say hi to my little girl. Right now I&amp;#39;m really far away, but I&amp;#39;ll come back very soon, okay?&amp;quot;&lt;/p&gt;\n\n&lt;p&gt;Samantha watches with a puzzled expression while Daisy babbles at the air, but her only response is to slowly shake her head. It&amp;#39;s clear from just one look that she thinks Daisy must be hallucinating my existence.&lt;/p&gt;\n\n&lt;p&gt;After I finish reassuring Daisy that her daddy &lt;em&gt;definitely&lt;/em&gt; isn&amp;#39;t dead, I say, &amp;quot;Oh, and tell aunt Samantha that daddy says hi, okay? Uh, tell her that mommy is fine, too. She got hurt a little bit, but daddy will definitely take care of her.&amp;quot;&lt;/p&gt;\n\n&lt;p&gt;Daisy nods furiously. &amp;quot;Okay! I love you, daddy! Come back soon!&amp;quot;&lt;/p&gt;\n\n&lt;p&gt;&amp;quot;I love you too, sweetheart.&amp;quot;&lt;/p&gt;\n\n&lt;p&gt;I try to kiss Daisy&amp;#39;s head, but my face awkwardly melts through her skull, allowing me to see her brains. &lt;em&gt;Ew!&lt;/em&gt;&lt;/p&gt;\n\n&lt;p&gt;With a shudder, I fly into the sky and disappear through the roof, leaving Daisy and Samantha behind.&lt;/p&gt;\n\n&lt;p&gt;...&lt;/p&gt;\n\n&lt;p&gt;Another few minutes later, I zip around the eastern side of Hero City. After scouting the area, I ready myself to return to Blinker to let her know about the situation outside the battlefield, only for my stomach to flip-flop in alarm!&lt;/p&gt;\n\n&lt;p&gt;Only a mile away from Hero City, several &amp;#39;blips&amp;#39; of soul energy show up within my vision range. I fly closer and gasp as I spot three glowing beacons of demonic mana standing around, talking to one another. The moment I get close enough, I listen intently to make out their conversation.&lt;/p&gt;\n\n&lt;p&gt;A demoness clothed in long, gray robes, growls at a male nearby. &amp;quot;-the signal. I think we should summon the gates now. We&amp;#39;ve already got the city surrounded. Once we build up our forces, we can rush the barrier all at once.&amp;quot;&lt;/p&gt;\n\n&lt;p&gt;&amp;quot;Ose&amp;#39;s orders are absolute,&amp;quot; The male says, his garb a green-colored bunch of robes. &amp;quot;We&amp;#39;re only Warpers. We don&amp;#39;t have the authority to override Emperor Ose. Do you think you&amp;#39;re smarter than her?&amp;quot;&lt;/p&gt;\n\n&lt;p&gt;The female&amp;#39;s expression crumples. &amp;quot;...No.&amp;quot;&lt;/p&gt;\n\n&lt;p&gt;&amp;quot;Then shut your trap and wait for the signal.&amp;quot;&lt;/p&gt;\n\n&lt;p&gt;My heart skips several beats as I gather that these three demons must have somehow skirted around the battlefield and slipped into our backlines! They&amp;#39;re waiting to open portals so they can attack us!&lt;/p&gt;\n\n&lt;p&gt;While I listen, my gaze falls on the third mana signature belonging to the demon who hasn&amp;#39;t spoken yet. To my surprise, not only is their mana signal far brighter than the other two, but the Warpers don&amp;#39;t look at the other demon for even a moment, as if that demon&amp;#39;s presence were invisible.&lt;/p&gt;\n\n&lt;p&gt;I draw a little closer and blink in surprise.&lt;/p&gt;\n\n&lt;p&gt;The third demon stands with their back to me. However, what surprises me the most is that my gaze pierces through part of their body!&lt;/p&gt;\n\n&lt;p&gt;With a start, I suddenly realize the other demon isn&amp;#39;t really there! Whoever they are, their presence is almost holographic and immaterial in nature, like me! They might be a fellow errant soul!&lt;/p&gt;\n\n&lt;p&gt;The moment I have this epiphany, the third demon suddenly stiffens. They turn around to look at me, revealing the face of a very familiar woman.&lt;/p&gt;\n\n&lt;p&gt;&lt;em&gt;Ose!&lt;/em&gt;&lt;/p&gt;\n\n&lt;p&gt;The Emperor of Infiltration stares at me for a moment and blanks out. &amp;quot;Hm? Another Astral Body? Who the Devil are you?&amp;quot;&lt;/p&gt;\n\n&lt;p&gt;In the blink of an eye, she rushes toward me, a look of venomous murder on her face. She soars into the sky and balls her hands into fists, aiming to pummel me into a bloody pulp. The instant before Ose arrives, she suddenly stops and reverses direction, her angry expression turning to shock and horror.&lt;/p&gt;\n\n&lt;p&gt;&amp;quot;What?! The Wordsmith?!&amp;quot;&lt;/p&gt;\n\n&lt;p&gt;My heart explodes with hatred and rage. I&amp;#39;ve suddenly stumbled upon a prime opportunity I never expected! Ose, now in a soul-body like mine, hovers mere feet away, clearly alarmed by my presence.&lt;/p&gt;\n\n&lt;p&gt;&amp;quot;Hello, &lt;em&gt;Ose.&lt;/em&gt; Seems you&amp;#39;ve been up to no good.&amp;quot;&lt;/p&gt;\n\n&lt;p&gt;Ose gnashes her teeth. &amp;quot;Tch! How dare you step within my domain, the Astral Realm! Now that you&amp;#39;ve seen my Astral Body, you&amp;#39;ve sealed your fate, Wordsmith!&amp;quot;&lt;/p&gt;\n\n&lt;p&gt;I shake my head.&lt;/p&gt;\n\n&lt;p&gt;&amp;quot;Oh, I don&amp;#39;t think so.&amp;quot;&lt;/p&gt;\n\n&lt;p&gt;&lt;strong&gt;&lt;a href=\"https://reddit.com/r/HFY/comments/iorzqa/the_cryopod_to_hell_252_astral_souleater/?\"&gt;Next Part&lt;/a&gt;&lt;/strong&gt;&lt;/p&gt;\n&lt;/div&gt;&lt;!-- SC_ON --&gt;", "likes": null, "suggested_sort": "confidence", "banned_at_utc": null, "view_count": null, "archived": false, "no_follow": false, "is_crosspostable": false, "pinned": false, "over_18": false, "all_awardings": [], "awarders": [], "media_only": false, "link_flair_template_id": "a6042884-fd8e-11e3-ae0c-12313d19304a", "can_gild": false, "spoiler": false, "locked": false, "author_flair_text": "Android", "treatment_tags": [], "visited": false, "removed_by": null, "num_reports": null, "distinguished": null, "subreddit_id": "t5_2y95n", "author_is_blocked": false, "mod_reason_by": null, "removal_reason": null, "link_flair_background_color": "", "id": "imz7sa", "is_robot_indexable": true, "num_duplicates": 0, "report_reasons": null, "author": "Klokinator", "discussion_type": null, "num_comments": 7, "send_replies": true, "media": null, "contest_mode": false, "author_patreon_flair": false, "author_flair_text_color": "dark", "permalink": "/r/HFY/comments/imz7sa/the_cryopod_to_hell_251_swift_soul_searching/", "stickied": false, "url": "https://www.reddit.com/r/HFY/comments/imz7sa/the_cryopod_to_hell_251_swift_soul_searching/", "subreddit_subscribers": 371487, "created_utc": 1599303393.0, "num_crossposts": 0, "mod_reports": [], "is_video": false}}], "before": null}}, {"kind": "Listing", "data": {"after": null, "dist": null, "modhash": "", "geo_filter": "", "children": [{"kind": "t1", "data": {"subreddit_id": "t5_2y95n", "approved_at_utc": null, "author_is_blocked": false, "comment_type": null, "awarders": [], "mod_reason_by": null, "banned_by": null, "author_flair_type": "text", "total_awards_received": 0, "subreddit": "HFY", "author_flair_template_id": "f2ef2e52-57dc-11e4-908c-12313b0e5086", "likes": null, "replies": "", "user_reports": [], "saved": false, "id": "g43xms7", "banned_at_utc": null, "mod_reason_title": null, "gilded": 0, "archived": false, "collapsed_reason_code": null, "no_follow": false, "author": "Klokinator", "can_mod_post": false, "created_utc": 1599303434.0, "send_replies": true, "parent_id": "t3_imz7sa", "score": 7, "author_fullname": "t2_fbfvm", "approved_by": null, "mod_note": null, "all_awardings": [], "collapsed": false, "body": "Hey all, Klok here!\n\nI should have finished this part yesterday, but like a big fat jerk, I got addicted to a new chinese novel and binged 150 chapters in one night and lost total track of time.\n\nThis part is really interesting! I'm now taking the time to really explore how souls 'work' and what Jason's soul-form can do. In the next part, we're going to get to see the Wordsmith go mano-a-mano with Ose in her Astral Body!\n\nBut is there a difference between an Astral Form and a Soul Body? Well, I guess we'll soon find out, won't we?\n\nCheck back in a few days! More Cryopod coming up!\n\n(Sidenote, after 252, I'll write a Cryoblog, then get back to TLP!)", "edited": false, "top_awarded_type": null, "author_flair_css_class": null, "name": "t1_g43xms7", "is_submitter": true, "downs": 0, "author_flair_richtext": [], "author_patreon_flair": false, "body_html": "&lt;div class=\"md\"&gt;&lt;p&gt;Hey all, Klok here!&lt;/p&gt;\n\n&lt;p&gt;I should have finished this part yesterday, but like a big fat jerk, I got addicted to a new chinese novel and binged 150 chapters in one night and lost total track of time.&lt;/p&gt;\n\n&lt;p&gt;This part is really interesting! I&amp;#39;m now taking the time to really explore how souls &amp;#39;work&amp;#39; and what Jason&amp;#39;s soul-form can do. In the next part, we&amp;#39;re going to get to see the Wordsmith go mano-a-mano with Ose in her Astral Body!&lt;/p&gt;\n\n&lt;p&gt;But is there a difference between an Astral Form and a Soul Body? Well, I guess we&amp;#39;ll soon find out, won&amp;#39;t we?&lt;/p&gt;\n\n&lt;p&gt;Check back in a few days! More Cryopod coming up!&lt;/p&gt;\n\n&lt;p&gt;(Sidenote, after 252, I&amp;#39;ll write a Cryoblog, then get back to TLP!)&lt;/p&gt;\n&lt;/div&gt;", "removal_reason": null, "collapsed_reason": null, "distinguished": null, "associated_award": null, "stickied": false, "author_premium": false, "can_gild": false, "gildings": {}, "unrepliable_reason": null, "author_flair_text_color": "dark", "score_hidden": false, "permalink": "/r/HFY/comments/imz7sa/the_cryopod_to_hell_251_swift_soul_searching/g43xms7/", "subreddit_type": "public", "locked": false, "report_reasons": null, "created": 1599303434.0, "author_flair_text": "Android", "treatment_tags": [], "link_id": "t3_imz7sa", "subreddit_name_prefixed": "r/HFY", "controversiality": 0, "depth": 0, "author_flair_background_color": null, "collapsed_because_crowd_control": null, "mod_reports": [], "num_reports": null, "ups": 7}}, {"kind": "t1", "data": {"subreddit_id": "t5_2y95n", "approved_at_utc": null, "author_is_blocked": false, "comment_type": null, "awarders": [], "mod_reason_by": null, "banned_by": null, "author_flair_type": "text", "total_awards_received": 0, "subreddit": "HFY", "author_flair_template_id": null, "likes": null, "replies": {"kind": "Listing", "data": {"after": null, "dist": null, "modhash": "", "geo_filter": "", "children": [{"kind": "t1", "data": {"subreddit_id": "t5_2y95n", "approved_at_utc": null, "author_is_blocked": false, "comment_type": null, "awarders": [], "mod_reason_by": null, "banned_by": null, "author_flair_type": "text", "total_awards_received": 0, "subreddit": "HFY", "author_flair_template_id": "f2ef2e52-57dc-11e4-908c-12313b0e5086", "likes": null, "replies": "", "user_reports": [], "saved": false, "id": "g43yfgy", "banned_at_utc": null, "mod_reason_title": null, "gilded": 0, "archived": false, "collapsed_reason_code": null, "no_follow": false, "author": "Klokinator", "can_mod_post": false, "created_utc": 1599303908.0, "send_replies": true, "parent_id": "t1_g43yboq", "score": 4, "author_fullname": "t2_fbfvm", "removal_reason": null, "approved_by": null, "mod_note": null, "all_awardings": [], "body": "Gotta get up to speed, fulfill that bodily need.", "edited": false, "top_awarded_type": null, "author_flair_css_class": null, "name": "t1_g43yfgy", "is_submitter": true, "downs": 0, "author_flair_richtext": [], "author_patreon_flair": false, "body_html": "&lt;div class=\"md\"&gt;&lt;p&gt;Gotta get up to speed, fulfill that bodily need.&lt;/p&gt;\n&lt;/div&gt;", "gildings": {}, "collapsed_reason": null, "distinguished": null, "associated_award": null, "stickied": false, "author_premium": false, "can_gild": false, "link_id": "t3_imz7sa", "unrepliable_reason": null, "author_flair_text_color": "dark", "score_hidden": false, "permalink": "/r/HFY/comments/imz7sa/the_cryopod_to_hell_251_swift_soul_searching/g43yfgy/", "subreddit_type": "public", "locked": false, "report_reasons": null, "created": 1599303908.0, "author_flair_text": "Android", "treatment_tags": [], "collapsed": false, "subreddit_name_prefixed": "r/HFY", "controversiality": 0, "depth": 1, "author_flair_background_color": null, "collapsed_because_crowd_control": null, "mod_reports": [], "num_reports": null, "ups": 4}}], "before": null}}, "user_reports": [], "saved": false, "id": "g43yboq", "banned_at_utc": null, "mod_reason_title": null, "gilded": 0, "archived": false, "collapsed_reason_code": null, "no_follow": true, "author": "Konrahd_Verdammt", "can_mod_post": false, "created_utc": 1599303845.0, "send_replies": true, "parent_id": "t3_imz7sa", "score": 3, "author_fullname": "t2_ylqw7", "approved_by": null, "mod_note": null, "all_awardings": [], "collapsed": false, "body": "Upvote then read, the proper way to proceed.", "edited": false, "top_awarded_type": null, "author_flair_css_class": null, "name": "t1_g43yboq", "is_submitter": false, "downs": 0, "author_flair_richtext": [], "author_patreon_flair": false, "body_html": "&lt;div class=\"md\"&gt;&lt;p&gt;Upvote then read, the proper way to proceed.&lt;/p&gt;\n&lt;/div&gt;", "removal_reason": null, "collapsed_reason": null, "distinguished": null, "associated_award": null, "stickied": false, "author_premium": false, "can_gild": false, "gildings": {}, "unrepliable_reason": null, "author_flair_text_color": null, "score_hidden": false, "permalink": "/r/HFY/comments/imz7sa/the_cryopod_to_hell_251_swift_soul_searching/g43yboq/", "subreddit_type": "public", "locked": false, "report_reasons": null, "created": 1599303845.0, "author_flair_text": null, "treatment_tags": [], "link_id": "t3_imz7sa", "subreddit_name_prefixed": "r/HFY", "controversiality": 0, "depth": 0, "author_flair_background_color": null, "collapsed_because_crowd_control": null, "mod_reports": [], "num_reports": null, "ups": 3}}, {"kind": "t1", "data": {"subreddit_id": "t5_2y95n", "approved_at_utc": null, "author_is_blocked": false, "comment_type": null, "awarders": [], "mod_reason_by": null, "banned_by": null, "author_flair_type": "text", "total_awards_received": 0, "subreddit": "HFY", "author_flair_template_id": null, "likes": null, "replies": "", "user_reports": [], "saved": false, "id": "g43xlbw", "banned_at_utc": null, "mod_reason_title": null, "gilded": 0, "archived": false, "collapsed_reason_code": null, "no_follow": true, "author": "UpdateMeBot", "can_mod_post": false, "created_utc": 1599303410.0, "send_replies": true, "parent_id": "t3_imz7sa", "score": 1, "author_fullname": "t2_zptge", "approved_by": null, "mod_note": null, "all_awardings": [], "collapsed": false, "body": "[Click here](https://www.reddit.com/message/compose/?to=UpdateMeBot&amp;subject=Subscribe&amp;message=SubscribeMe%20u%2FKlokinator%20r%2FHFY) to subscribe to u/Klokinator and receive a message every time they post.\n\n*****\n\n|[^(Info)](https://www.reddit.com/r/UpdateMeBot/comments/ggotgx/updatemebot_info_v20/)|[^(Request Update)](https://www.reddit.com/message/compose/?to=UpdateMeBot&amp;subject=Update&amp;message=SubscribeMe%21%20u%2Fusername%20r%2Fsubreddit)|[^(Your Updates)](https://www.reddit.com/message/compose/?to=UpdateMeBot&amp;subject=List%20Of%20Updates&amp;message=MyUpdates)|[^(Feedback)](https://www.reddit.com/message/compose/?to=Watchful1&amp;subject=UpdateMeBot%20Feedback)|\n|-|-|-|-|", "edited": false, "top_awarded_type": null, "author_flair_css_class": null, "name": "t1_g43xlbw", "is_submitter": false, "downs": 0, "author_flair_richtext": [], "author_patreon_flair": false, "body_html": "&lt;div class=\"md\"&gt;&lt;p&gt;&lt;a href=\"https://www.reddit.com/message/compose/?to=UpdateMeBot&amp;amp;subject=Subscribe&amp;amp;message=SubscribeMe%20u%2FKlokinator%20r%2FHFY\"&gt;Click here&lt;/a&gt; to subscribe to &lt;a href=\"/u/Klokinator\"&gt;u/Klokinator&lt;/a&gt; and receive a message every time they post.&lt;/p&gt;\n\n&lt;hr/&gt;\n\n&lt;table&gt;&lt;thead&gt;\n&lt;tr&gt;\n&lt;th&gt;&lt;a href=\"https://www.reddit.com/r/UpdateMeBot/comments/ggotgx/updatemebot_info_v20/\"&gt;&lt;sup&gt;Info&lt;/sup&gt;&lt;/a&gt;&lt;/th&gt;\n&lt;th&gt;&lt;a href=\"https://www.reddit.com/message/compose/?to=UpdateMeBot&amp;amp;subject=Update&amp;amp;message=SubscribeMe%21%20u%2Fusername%20r%2Fsubreddit\"&gt;&lt;sup&gt;Request Update&lt;/sup&gt;&lt;/a&gt;&lt;/th&gt;\n&lt;th&gt;&lt;a href=\"https://www.reddit.com/message/compose/?to=UpdateMeBot&amp;amp;subject=List%20Of%20Updates&amp;amp;message=MyUpdates\"&gt;&lt;sup&gt;Your Updates&lt;/sup&gt;&lt;/a&gt;&lt;/th&gt;\n&lt;th&gt;&lt;a href=\"https://www.reddit.com/message/compose/?to=Watchful1&amp;amp;subject=UpdateMeBot%20Feedback\"&gt;&lt;sup&gt;Feedback&lt;/sup&gt;&lt;/a&gt;&lt;/th&gt;\n&lt;/tr&gt;\n&lt;/thead&gt;&lt;tbody&gt;\n&lt;/tbody&gt;&lt;/table&gt;\n&lt;/div&gt;", "removal_reason": null, "collapsed_reason": null, "distinguished": null, "associated_award": null, "stickied": false, "author_premium": false, "can_gild": false, "gildings": {}, "unrepliable_reason": null, "author_flair_text_color": null, "score_hidden": false, "permalink": "/r/HFY/comments/imz7sa/the_cryopod_to_hell_251_swift_soul_searching/g43xlbw/", "subreddit_type": "public", "locked": false, "report_reasons": null, "created": 1599303410.0, "author_flair_text": null, "treatment_tags": [], "link_id": "t3_imz7sa", "subreddit_name_prefixed": "r/HFY", "controversiality": 0, "depth": 0, "author_flair_background_color": null, "collapsed_because_crowd_control": null, "mod_reports": [], "num_reports": null, "ups": 1}}, {"kind": "t1", "data": {"subreddit_id": "t5_2y95n", "approved_at_utc": null, "author_is_blocked": false, "comment_type": null, "awarders": [], "mod_reason_by": null, "banned_by": null, "author_flair_type": "text", "total_awards_received": 0, "subreddit": "HFY", "author_flair_template_id": null, "likes": null, "replies": "", "user_reports": [], "saved": false, "id": "g43xmja", "banned_at_utc": null, "mod_reason_title": null, "gilded": 0, "archived": false, "collapsed_reason_code": null, "no_follow": true, "author": "HFYWaffle", "can_mod_post": false, "created_utc": 1599303430.0, "send_replies": true, "parent_id": "t3_imz7sa", "score": 1, "author_fullname": "t2_3ynn53vi", "approved_by": null, "mod_note": null, "all_awardings": [], "collapsed": false, "body": "/u/Klokinator ([wiki](https://www.reddit.com/r/HFY/wiki/authors/Klokinator)) has posted 275 other stories, including: \n\n \n* [The Cryopod to Hell 250: The Battle Brothers' Resurgence!](https://www.reddit.com/r/HFY/comments/iki80y/the_cryopod_to_hell_250_the_battle_brothers/)\n* [The Cryopod to Hell 249: Mara's Great Escape!](https://www.reddit.com/r/HFY/comments/iiqj93/the_cryopod_to_hell_249_maras_great_escape/)\n* [The Cryopod to Hell 248: Wordsmith.exe](https://www.reddit.com/r/HFY/comments/ihj43n/the_cryopod_to_hell_248_wordsmithexe/)\n* [\\[Cryoverse\\] The Last Precursor 022: Admiral Rodriguez, the True Troll](https://www.reddit.com/r/HFY/comments/idvlix/cryoverse_the_last_precursor_022_admiral/)\n* [\\[Cryoverse\\] The Last Precursor 021: The Bloodbearer's Holodeck](https://www.reddit.com/r/HFY/comments/icmthf/cryoverse_the_last_precursor_021_the_bloodbearers/)\n* [\\[Cryoverse\\] The Last Precursor 020: Rapid Reconstruction!](https://www.reddit.com/r/HFY/comments/ibd2v9/cryoverse_the_last_precursor_020_rapid/)\n* [\\[Cryoverse\\] The Last Precursor 019: Terrans Love Kittens](https://www.reddit.com/r/HFY/comments/ia7lcg/cryoverse_the_last_precursor_019_terrans_love/)\n* [\\[Cryoverse\\] The Last Precursor 018: The Th\u00fclvik's Cunning](https://www.reddit.com/r/HFY/comments/i8yp2f/cryoverse_the_last_precursor_018_the_th\u00fclviks/)\n* [\\[Cryoverse\\] The Last Precursor 017: The Th\u00fclvik](https://www.reddit.com/r/HFY/comments/i73hew/cryoverse_the_last_precursor_017_the_th\u00fclvik/)\n* [\\[Cryoverse\\] The Last Precursor 016: What killed Humanity?](https://www.reddit.com/r/HFY/comments/i5y5jh/cryoverse_the_last_precursor_016_what_killed/)\n* [\\[Cryoverse\\] The Last Precursor 015: The Bloodbearer's Food Crisis](https://www.reddit.com/r/HFY/comments/i5clt7/cryoverse_the_last_precursor_015_the_bloodbearers/)\n* [The Cryopod to Hell 247: Jason's Attack!](https://www.reddit.com/r/HFY/comments/i44kdn/the_cryopod_to_hell_247_jasons_attack/)\n* [\\[Absurdverse\\] Earth's Resources Will Be Ours! (\"Stupid Humans\" Prequel!)](https://www.reddit.com/r/HFY/comments/i2wy6f/absurdverse_earths_resources_will_be_ours_stupid/)\n* [The Cryopod to Hell 246: The Wordsmith Returns](https://www.reddit.com/r/HFY/comments/i2ac6c/the_cryopod_to_hell_246_the_wordsmith_returns/)\n* [The Cryopod to Hell 245: Prison Break!](https://www.reddit.com/r/HFY/comments/i15xy9/the_cryopod_to_hell_245_prison_break/)\n* [\\[Comedy\\] Stupid Humans!](https://www.reddit.com/r/HFY/comments/hz3517/comedy_stupid_humans/)\n* [The Cryopod to Hell 244: Darkness](https://www.reddit.com/r/HFY/comments/hy6nwo/the_cryopod_to_hell_244_darkness/)\n* [\\[Cryoverse\\] The Last Precursor 014: Advanced Warp Theory](https://www.reddit.com/r/HFY/comments/hwzyro/cryoverse_the_last_precursor_014_advanced_warp/)\n* [\\[Cryoverse\\] The Last Precursor 013: Repairing the Bloodbearer](https://www.reddit.com/r/HFY/comments/hv70g9/cryoverse_the_last_precursor_013_repairing_the/)\n* [\\[Cryoverse\\] The Last Precursor 012: My Vision Is Augmented](https://www.reddit.com/r/HFY/comments/hukh6b/cryoverse_the_last_precursor_012_my_vision_is/)\n* [\\[Cryoverse\\] The Last Precursor 011: Megla's Honesty](https://www.reddit.com/r/HFY/comments/hu04u0/cryoverse_the_last_precursor_011_meglas_honesty/)\n* [\\[Cryoverse\\] The Last Precursor 010: Terran Power Levels](https://www.reddit.com/r/HFY/comments/hswixb/cryoverse_the_last_precursor_010_terran_power/)\n* [The Cryopod to Hell 243: Mephisto's Counterattack](https://www.reddit.com/r/HFY/comments/hrmh1p/the_cryopod_to_hell_243_mephistos_counterattack/)\n* [The Cryopod to Hell 242: Pandemonium](https://www.reddit.com/r/HFY/comments/hpx8qp/the_cryopod_to_hell_242_pandemonium/)\n* [The Cryopod to Hell 241: Invasion!](https://www.reddit.com/r/HFY/comments/honvbi/the_cryopod_to_hell_241_invasion/) \n\nThis list was automatically generated by `Waffle v.3.5.0 'Toast'`. \n\nContact [GamingWolfie](https://www.reddit.com/message/compose?to=GamingWolfie&amp;subject=Waffl%E1%B5%A53) or [message the mods](https://www.reddit.com/message/compose?to=%2Fr%2FHFY&amp;subject=Waffl%E1%B5%A53) if you have any issues.", "edited": false, "top_awarded_type": null, "author_flair_css_class": null, "name": "t1_g43xmja", "is_submitter": false, "downs": 0, "author_flair_richtext": [], "author_patreon_flair": false, "body_html": "&lt;div class=\"md\"&gt;&lt;p&gt;&lt;a href=\"/u/Klokinator\"&gt;/u/Klokinator&lt;/a&gt; (&lt;a href=\"https://www.reddit.com/r/HFY/wiki/authors/Klokinator\"&gt;wiki&lt;/a&gt;) has posted 275 other stories, including: &lt;/p&gt;\n\n&lt;ul&gt;\n&lt;li&gt;&lt;a href=\"https://www.reddit.com/r/HFY/comments/iki80y/the_cryopod_to_hell_250_the_battle_brothers/\"&gt;The Cryopod to Hell 250: The Battle Brothers&amp;#39; Resurgence!&lt;/a&gt;&lt;/li&gt;\n&lt;li&gt;&lt;a href=\"https://www.reddit.com/r/HFY/comments/iiqj93/the_cryopod_to_hell_249_maras_great_escape/\"&gt;The Cryopod to Hell 249: Mara&amp;#39;s Great Escape!&lt;/a&gt;&lt;/li&gt;\n&lt;li&gt;&lt;a href=\"https://www.reddit.com/r/HFY/comments/ihj43n/the_cryopod_to_hell_248_wordsmithexe/\"&gt;The Cryopod to Hell 248: Wordsmith.exe&lt;/a&gt;&lt;/li&gt;\n&lt;li&gt;&lt;a href=\"https://www.reddit.com/r/HFY/comments/idvlix/cryoverse_the_last_precursor_022_admiral/\"&gt;[Cryoverse] The Last Precursor 022: Admiral Rodriguez, the True Troll&lt;/a&gt;&lt;/li&gt;\n&lt;li&gt;&lt;a href=\"https://www.reddit.com/r/HFY/comments/icmthf/cryoverse_the_last_precursor_021_the_bloodbearers/\"&gt;[Cryoverse] The Last Precursor 021: The Bloodbearer&amp;#39;s Holodeck&lt;/a&gt;&lt;/li&gt;\n&lt;li&gt;&lt;a href=\"https://www.reddit.com/r/HFY/comments/ibd2v9/cryoverse_the_last_precursor_020_rapid/\"&gt;[Cryoverse] The Last Precursor 020: Rapid Reconstruction!&lt;/a&gt;&lt;/li&gt;\n&lt;li&gt;&lt;a href=\"https://www.reddit.com/r/HFY/comments/ia7lcg/cryoverse_the_last_precursor_019_terrans_love/\"&gt;[Cryoverse] The Last Precursor 019: Terrans Love Kittens&lt;/a&gt;&lt;/li&gt;\n&lt;li&gt;&lt;a href=\"https://www.reddit.com/r/HFY/comments/i8yp2f/cryoverse_the_last_precursor_018_the_th%C3%BClviks/\"&gt;[Cryoverse] The Last Precursor 018: The Th\u00fclvik&amp;#39;s Cunning&lt;/a&gt;&lt;/li&gt;\n&lt;li&gt;&lt;a href=\"https://www.reddit.com/r/HFY/comments/i73hew/cryoverse_the_last_precursor_017_the_th%C3%BClvik/\"&gt;[Cryoverse] The Last Precursor 017: The Th\u00fclvik&lt;/a&gt;&lt;/li&gt;\n&lt;li&gt;&lt;a href=\"https://www.reddit.com/r/HFY/comments/i5y5jh/cryoverse_the_last_precursor_016_what_killed/\"&gt;[Cryoverse] The Last Precursor 016: What killed Humanity?&lt;/a&gt;&lt;/li&gt;\n&lt;li&gt;&lt;a href=\"https://www.reddit.com/r/HFY/comments/i5clt7/cryoverse_the_last_precursor_015_the_bloodbearers/\"&gt;[Cryoverse] The Last Precursor 015: The Bloodbearer&amp;#39;s Food Crisis&lt;/a&gt;&lt;/li&gt;\n&lt;li&gt;&lt;a href=\"https://www.reddit.com/r/HFY/comments/i44kdn/the_cryopod_to_hell_247_jasons_attack/\"&gt;The Cryopod to Hell 247: Jason&amp;#39;s Attack!&lt;/a&gt;&lt;/li&gt;\n&lt;li&gt;&lt;a href=\"https://www.reddit.com/r/HFY/comments/i2wy6f/absurdverse_earths_resources_will_be_ours_stupid/\"&gt;[Absurdverse] Earth&amp;#39;s Resources Will Be Ours! (&amp;quot;Stupid Humans&amp;quot; Prequel!)&lt;/a&gt;&lt;/li&gt;\n&lt;li&gt;&lt;a href=\"https://www.reddit.com/r/HFY/comments/i2ac6c/the_cryopod_to_hell_246_the_wordsmith_returns/\"&gt;The Cryopod to Hell 246: The Wordsmith Returns&lt;/a&gt;&lt;/li&gt;\n&lt;li&gt;&lt;a href=\"https://www.reddit.com/r/HFY/comments/i15xy9/the_cryopod_to_hell_245_prison_break/\"&gt;The Cryopod to Hell 245: Prison Break!&lt;/a&gt;&lt;/li&gt;\n&lt;li&gt;&lt;a href=\"https://www.reddit.com/r/HFY/comments/hz3517/comedy_stupid_humans/\"&gt;[Comedy] Stupid Humans!&lt;/a&gt;&lt;/li&gt;\n&lt;li&gt;&lt;a href=\"https://www.reddit.com/r/HFY/comments/hy6nwo/the_cryopod_to_hell_244_darkness/\"&gt;The Cryopod to Hell 244: Darkness&lt;/a&gt;&lt;/li&gt;\n&lt;li&gt;&lt;a href=\"https://www.reddit.com/r/HFY/comments/hwzyro/cryoverse_the_last_precursor_014_advanced_warp/\"&gt;[Cryoverse] The Last Precursor 014: Advanced Warp Theory&lt;/a&gt;&lt;/li&gt;\n&lt;li&gt;&lt;a href=\"https://www.reddit.com/r/HFY/comments/hv70g9/cryoverse_the_last_precursor_013_repairing_the/\"&gt;[Cryoverse] The Last Precursor 013: Repairing the Bloodbearer&lt;/a&gt;&lt;/li&gt;\n&lt;li&gt;&lt;a href=\"https://www.reddit.com/r/HFY/comments/hukh6b/cryoverse_the_last_precursor_012_my_vision_is/\"&gt;[Cryoverse] The Last Precursor 012: My Vision Is Augmented&lt;/a&gt;&lt;/li&gt;\n&lt;li&gt;&lt;a href=\"https://www.reddit.com/r/HFY/comments/hu04u0/cryoverse_the_last_precursor_011_meglas_honesty/\"&gt;[Cryoverse] The Last Precursor 011: Megla&amp;#39;s Honesty&lt;/a&gt;&lt;/li&gt;\n&lt;li&gt;&lt;a href=\"https://www.reddit.com/r/HFY/comments/hswixb/cryoverse_the_last_precursor_010_terran_power/\"&gt;[Cryoverse] The Last Precursor 010: Terran Power Levels&lt;/a&gt;&lt;/li&gt;\n&lt;li&gt;&lt;a href=\"https://www.reddit.com/r/HFY/comments/hrmh1p/the_cryopod_to_hell_243_mephistos_counterattack/\"&gt;The Cryopod to Hell 243: Mephisto&amp;#39;s Counterattack&lt;/a&gt;&lt;/li&gt;\n&lt;li&gt;&lt;a href=\"https://www.reddit.com/r/HFY/comments/hpx8qp/the_cryopod_to_hell_242_pandemonium/\"&gt;The Cryopod to Hell 242: Pandemonium&lt;/a&gt;&lt;/li&gt;\n&lt;li&gt;&lt;a href=\"https://www.reddit.com/r/HFY/comments/honvbi/the_cryopod_to_hell_241_invasion/\"&gt;The Cryopod to Hell 241: Invasion!&lt;/a&gt; &lt;/li&gt;\n&lt;/ul&gt;\n\n&lt;p&gt;This list was automatically generated by &lt;code&gt;Waffle v.3.5.0 &amp;#39;Toast&amp;#39;&lt;/code&gt;. &lt;/p&gt;\n\n&lt;p&gt;Contact &lt;a href=\"https://www.reddit.com/message/compose?to=GamingWolfie&amp;amp;subject=Waffl%E1%B5%A53\"&gt;GamingWolfie&lt;/a&gt; or &lt;a href=\"https://www.reddit.com/message/compose?to=%2Fr%2FHFY&amp;amp;subject=Waffl%E1%B5%A53\"&gt;message the mods&lt;/a&gt; if you have any issues.&lt;/p&gt;\n&lt;/div&gt;", "removal_reason": null, "collapsed_reason": null, "distinguished": null, "associated_award": null, "stickied": false, "author_premium": false, "can_gild": false, "gildings": {}, "unrepliable_reason": null, "author_flair_text_color": "dark", "score_hidden": false, "permalink": "/r/HFY/comments/imz7sa/the_cryopod_to_hell_251_swift_soul_searching/g43xmja/", "subreddit_type": "public", "locked": false, "report_reasons": null, "created": 1599303430.0, "author_flair_text": "W\u1d654ffle", "treatment_tags": [], "link_id": "t3_imz7sa", "subreddit_name_prefixed": "r/HFY", "controversiality": 0, "depth": 0, "author_flair_background_color": "", "collapsed_because_crowd_control": null, "mod_reports": [], "num_reports": null, "ups": 1}}, {"kind": "t1", "data": {"subreddit_id": "t5_2y95n", "approved_at_utc": null, "author_is_blocked": false, "comment_type": null, "awarders": [], "mod_reason_by": null, "banned_by": null, "author_flair_type": "text", "total_awards_received": 0, "subreddit": "HFY", "author_flair_template_id": "afb84c44-012a-11e4-bf19-12313b0e95bd", "likes": null, "replies": {"kind": "Listing", "data": {"after": null, "dist": null, "modhash": "", "geo_filter": "", "children": [{"kind": "t1", "data": {"subreddit_id": "t5_2y95n", "approved_at_utc": null, "author_is_blocked": false, "comment_type": null, "awarders": [], "mod_reason_by": null, "banned_by": null, "author_flair_type": "text", "total_awards_received": 0, "subreddit": "HFY", "author_flair_template_id": "f2ef2e52-57dc-11e4-908c-12313b0e5086", "likes": null, "replies": "", "user_reports": [], "saved": false, "id": "g44mxn9", "banned_at_utc": null, "mod_reason_title": null, "gilded": 0, "archived": false, "collapsed_reason_code": null, "no_follow": true, "author": "Klokinator", "can_mod_post": false, "created_utc": 1599316848.0, "send_replies": true, "parent_id": "t1_g44mv81", "score": 3, "author_fullname": "t2_fbfvm", "removal_reason": null, "approved_by": null, "mod_note": null, "all_awardings": [], "body": "I can promise it will be very interesting!", "edited": false, "top_awarded_type": null, "author_flair_css_class": null, "name": "t1_g44mxn9", "is_submitter": true, "downs": 0, "author_flair_richtext": [], "author_patreon_flair": false, "body_html": "&lt;div class=\"md\"&gt;&lt;p&gt;I can promise it will be very interesting!&lt;/p&gt;\n&lt;/div&gt;", "gildings": {}, "collapsed_reason": null, "distinguished": null, "associated_award": null, "stickied": false, "author_premium": false, "can_gild": false, "link_id": "t3_imz7sa", "unrepliable_reason": null, "author_flair_text_color": "dark", "score_hidden": false, "permalink": "/r/HFY/comments/imz7sa/the_cryopod_to_hell_251_swift_soul_searching/g44mxn9/", "subreddit_type": "public", "locked": false, "report_reasons": null, "created": 1599316848.0, "author_flair_text": "Android", "treatment_tags": [], "collapsed": false, "subreddit_name_prefixed": "r/HFY", "controversiality": 0, "depth": 1, "author_flair_background_color": null, "collapsed_because_crowd_control": null, "mod_reports": [], "num_reports": null, "ups": 3}}], "before": null}}, "user_reports": [], "saved": false, "id": "g44mv81", "banned_at_utc": null, "mod_reason_title": null, "gilded": 0, "archived": false, "collapsed_reason_code": null, "no_follow": true, "author": "Portal10101", "can_mod_post": false, "created_utc": 1599316819.0, "send_replies": true, "parent_id": "t3_imz7sa", "score": 1, "author_fullname": "t2_4aobfcr6", "approved_by": null, "mod_note": null, "all_awardings": [], "collapsed": false, "body": "Well this could go good or bad for either side. Hopefully Jason hasn\u2019t underestimated Ose.", "edited": false, "top_awarded_type": null, "author_flair_css_class": null, "name": "t1_g44mv81", "is_submitter": false, "downs": 0, "author_flair_richtext": [], "author_patreon_flair": false, "body_html": "&lt;div class=\"md\"&gt;&lt;p&gt;Well this could go good or bad for either side. Hopefully Jason hasn\u2019t underestimated Ose.&lt;/p&gt;\n&lt;/div&gt;", "removal_reason": null, "collapsed_reason": null, "distinguished": null, "associated_award": null, "stickied": false, "author_premium": false, "can_gild": false, "gildings": {}, "unrepliable_reason": null, "author_flair_text_color": "dark", "score_hidden": false, "permalink": "/r/HFY/comments/imz7sa/the_cryopod_to_hell_251_swift_soul_searching/g44mv81/", "subreddit_type": "public", "locked": false, "report_reasons": null, "created": 1599316819.0, "author_flair_text": "Human", "treatment_tags": [], "link_id": "t3_imz7sa", "subreddit_name_prefixed": "r/HFY", "controversiality": 0, "depth": 0, "author_flair_background_color": null, "collapsed_because_crowd_control": null, "mod_reports": [], "num_reports": null, "ups": 1}}], "before": null}}]