{
  "subreddit": "TheCryopodToHell",
  "author": "Klokinator",
  "created": 1727797869.0,
  "created_utc": 1727797869.0,
  "edited": false,
  "ups": 49,
  "downs": 0,
  "score": 49,
  "upvote_ratio": 1.0,
  "title": "Cryopod Refresh 589: Energon",
  "gilded": 0,
  "replies": [
    {
      "subreddit": "TheCryopodToHell",
      "author": "Klokinator",
      "created": 1727797951.0,
      "created_utc": 1727797951.0,
      "edited": false,
      "ups": 12,
      "downs": 0,
      "score": 12,
      "controversiality": 0,
      "body": "What? Two parts in two days?\n\nI can't believe it. The legends said it was no longer possible...",
      "body_html": "&lt;div class=\"md\"&gt;&lt;p&gt;What? Two parts in two days?&lt;/p&gt;\n\n&lt;p&gt;I can&amp;#39;t believe it. The legends said it was no longer possible...&lt;/p&gt;\n&lt;/div&gt;",
      "author_flair_text": null,
      "author_flair_richtext": [],
      "author_flair_text_color": null,
      "author_flair_css_class": null,
      "distinguished": null,
      "stickied": false,
      "depth": 0,
      "replies": ""
    },
    {
      "subreddit": "TheCryopodToHell",
      "author": "Complex-Movie-5180",
      "created": 1727798483.0,
      "created_utc": 1727798483.0,
      "edited": false,
      "ups": 7,
      "downs": 0,
      "score": 7,
      "controversiality": 0,
      "body": "Hell yeah.  Crankin out the parts and getting closer to the GS. Anxiously awaiting to see how everything is about to explode into pure Chaos.",
      "body_html": "&lt;div class=\"md\"&gt;&lt;p&gt;Hell yeah.  Crankin out the parts and getting closer to the GS. Anxiously awaiting to see how everything is about to explode into pure Chaos.&lt;/p&gt;\n&lt;/div&gt;",
      "author_flair_text": null,
      "author_flair_richtext": [],
      "author_flair_text_color": null,
      "author_flair_css_class": null,
      "distinguished": null,
      "stickied": false,
      "depth": 0,
      "replies": ""
    },
    {
      "subreddit": "TheCryopodToHell",
      "author": "supremeaesthete",
      "created": 1727799117.0,
      "created_utc": 1727799117.0,
      "edited": false,
      "ups": 6,
      "downs": 0,
      "score": 6,
      "controversiality": 0,
      "body": "Oh wow, like a 2-for-1 deal!",
      "body_html": "&lt;div class=\"md\"&gt;&lt;p&gt;Oh wow, like a 2-for-1 deal!&lt;/p&gt;\n&lt;/div&gt;",
      "author_flair_text": null,
      "author_flair_richtext": [],
      "author_flair_text_color": null,
      "author_flair_css_class": null,
      "distinguished": null,
      "stickied": false,
      "depth": 0,
      "replies": ""
    },
    {
      "subreddit": "TheCryopodToHell",
      "author": "VulturE",
      "created": 1727801334.0,
      "created_utc": 1727801334.0,
      "edited": false,
      "ups": 5,
      "downs": 0,
      "score": 5,
      "controversiality": 0,
      "body": "I literally cannot wait to see more of Bael.",
      "body_html": "&lt;div class=\"md\"&gt;&lt;p&gt;I literally cannot wait to see more of Bael.&lt;/p&gt;\n&lt;/div&gt;",
      "author_flair_text": null,
      "author_flair_richtext": [],
      "author_flair_text_color": null,
      "author_flair_css_class": null,
      "distinguished": null,
      "stickied": false,
      "depth": 0,
      "replies": ""
    },
    {
      "subreddit": "TheCryopodToHell",
      "author": "Frigentus",
      "created": 1727924583.0,
      "created_utc": 1727924583.0,
      "edited": false,
      "ups": 2,
      "downs": 0,
      "score": 2,
      "controversiality": 0,
      "body": "Hope: Finally! With Excalibur in my possession, I now have a supply of mana that rivals the Phoenix Cube!\n\nMeanwhile Jason: yeah can I get a fucking uhhhhhhhhhhhhhhhhhhhhhhhhhhh one hundred stars with an extra large 99% conversion-loss ratio with some fries thanks",
      "body_html": "&lt;div class=\"md\"&gt;&lt;p&gt;Hope: Finally! With Excalibur in my possession, I now have a supply of mana that rivals the Phoenix Cube!&lt;/p&gt;\n\n&lt;p&gt;Meanwhile Jason: yeah can I get a fucking uhhhhhhhhhhhhhhhhhhhhhhhhhhh one hundred stars with an extra large 99% conversion-loss ratio with some fries thanks&lt;/p&gt;\n&lt;/div&gt;",
      "author_flair_text": "Big Brain Frig",
      "author_flair_richtext": [],
      "author_flair_text_color": "dark",
      "author_flair_css_class": "donor1",
      "distinguished": null,
      "stickied": false,
      "depth": 0,
      "replies": ""
    }
  ]
}